easy_start_wisharetec/__init__.py
easy_start_wisharetec/scaasp.py
easy_start_wisharetec/shanshu.py
easy_start_wisharetec-0.1.0.dist-info/licenses/LICENSE
easy_start_wisharetec-0.1.0.dist-info/METADATA
easy_start_wisharetec-0.1.0.dist-info/WHEEL
easy_start_wisharetec-0.1.0.dist-info/top_level.txt
easy_start_wisharetec-0.1.0.dist-info/RECORD
